{
    "naersk": {
        "branch": "master",
        "description": "Build rust crates in Nix. No configuration, no code generation, no IFD. Sandbox friendly.",
        "homepage": "",
        "owner": "nmattia",
        "repo": "naersk",
        "rev": "14997a79cd78fe34ad6390f18a327ee0593e5eec",
        "sha256": "1g8r0idblr4qv0xc79z2qxk2x44kh2bqxjx95li1lqn96264g318",
        "type": "tarball",
        "url": "https://github.com/nmattia/naersk/archive/14997a79cd78fe34ad6390f18a327ee0593e5eec.tar.gz",
        "url_template": "https://github.com/<owner>/<repo>/archive/<rev>.tar.gz"
    },
    "napalm": {
        "branch": "master",
        "description": "Support for building npm packages in Nix and lightweight npm registry",
        "homepage": "",
        "owner": "nmattia",
        "repo": "napalm",
        "rev": "4717e59f702303704b46b1e27ede6f17aa4f0f6c",
        "sha256": "14y0l2in8hjxf35f0fgmirl512q7bj2fzy8vn6rh9gxflz93b737",
        "type": "tarball",
        "url": "https://github.com/nmattia/napalm/archive/4717e59f702303704b46b1e27ede6f17aa4f0f6c.tar.gz",
        "url_template": "https://github.com/<owner>/<repo>/archive/<rev>.tar.gz"
    },
    "nix-based-sandbox": {
        "branch": "master",
        "description": null,
        "homepage": null,
        "owner": "pastebinrun",
        "repo": "nix-based-sandbox",
        "rev": "8e7b4cbd262e098d90de616ddc7ee68d28169ce3",
        "sha256": "14vb71v58ny8gy2d9ligi1hxpfnbwgixzward9kv70590cmxz74n",
        "type": "tarball",
        "url": "https://github.com/pastebinrun/nix-based-sandbox/archive/8e7b4cbd262e098d90de616ddc7ee68d28169ce3.tar.gz",
        "url_template": "https://github.com/<owner>/<repo>/archive/<rev>.tar.gz"
    },
    "pastebinrun": {
        "branch": "master",
        "description": null,
        "homepage": null,
        "owner": "pastebinrun",
        "repo": "pastebinrun",
        "rev": "98b9dfce3466d455fc85f653cc7f4fc615cd170c",
        "sha256": "17q9yls5hb21h7fmz0ay29d2kkar97p4xxcbxkrrk6vpkvwpvwds",
        "type": "tarball",
        "url": "https://github.com/pastebinrun/pastebinrun/archive/98b9dfce3466d455fc85f653cc7f4fc615cd170c.tar.gz",
        "url_template": "https://github.com/<owner>/<repo>/archive/<rev>.tar.gz"
    },
    "pulldown-cmark-babelmark": {
        "branch": "master",
        "description": null,
        "homepage": null,
        "owner": "xfix",
        "repo": "pulldown-cmark-babelmark",
        "rev": "dfefde9807915ee1d1acf1c299390864b4527b76",
        "sha256": "0w5zh4r1cg9f78ln2957agmjn95sq7z9isbm2s7v7avf6bs8zy77",
        "type": "tarball",
        "url": "https://github.com/xfix/pulldown-cmark-babelmark/archive/dfefde9807915ee1d1acf1c299390864b4527b76.tar.gz",
        "url_template": "https://github.com/<owner>/<repo>/archive/<rev>.tar.gz"
    },
    "xbot": {
        "branch": "master",
        "description": null,
        "homepage": null,
        "owner": "xfix",
        "repo": "xbot",
        "rev": "4d765f7a28d9530c1195b0ed30f0cb678c615428",
        "sha256": "0vjn6ld3wwzzy9h58k2v86rq07mr85gnv1pmimbi1q0rmqnk2m8j",
        "type": "tarball",
        "url": "https://github.com/xfix/xbot/archive/4d765f7a28d9530c1195b0ed30f0cb678c615428.tar.gz",
        "url_template": "https://github.com/<owner>/<repo>/archive/<rev>.tar.gz"
    }
}
