{
    "naersk": {
        "branch": "master",
        "description": "Build rust crates in Nix. No configuration, no code generation, no IFD. Sandbox friendly.",
        "homepage": "",
        "owner": "nmattia",
        "repo": "naersk",
        "rev": "d998160d6a076cfe8f9741e56aeec7e267e3e114",
        "sha256": "1s10ygdsi17zjfiypwj7bhxys6yxws10hhq3ckfl3996v2q04d3v",
        "type": "tarball",
        "url": "https://github.com/nmattia/naersk/archive/d998160d6a076cfe8f9741e56aeec7e267e3e114.tar.gz",
        "url_template": "https://github.com/<owner>/<repo>/archive/<rev>.tar.gz"
    },
    "napalm": {
        "branch": "master",
        "description": "Support for building npm packages in Nix and lightweight npm registry",
        "homepage": "",
        "owner": "nmattia",
        "repo": "napalm",
        "rev": "7c25a05cef52dc405f4688422ce0046ca94aadcf",
        "sha256": "0aff7rikmyy4c2h6981vcv2n05xvllh2dqkhqxgz80z2nfapm7wb",
        "type": "tarball",
        "url": "https://github.com/nmattia/napalm/archive/7c25a05cef52dc405f4688422ce0046ca94aadcf.tar.gz",
        "url_template": "https://github.com/<owner>/<repo>/archive/<rev>.tar.gz"
    },
    "nix-based-sandbox": {
        "branch": "master",
        "description": null,
        "homepage": null,
        "owner": "pastebinrun",
        "repo": "nix-based-sandbox",
        "rev": "2801afa95e15166a5ee81b0aac89f3ce779e572c",
        "sha256": "110vsdghyqbks76mlriyvdzv4d7j9n9xnl583249789nvpn0ifml",
        "type": "tarball",
        "url": "https://github.com/pastebinrun/nix-based-sandbox/archive/2801afa95e15166a5ee81b0aac89f3ce779e572c.tar.gz",
        "url_template": "https://github.com/<owner>/<repo>/archive/<rev>.tar.gz"
    },
    "pastebinrun": {
        "branch": "master",
        "description": null,
        "homepage": null,
        "owner": "pastebinrun",
        "repo": "pastebinrun",
        "rev": "bc6a669b107085d54c9dfd9f65ed402c3431460e",
        "sha256": "0ciz3wyz8jljfzjykl4g61rch63cc9b2b0yx6xg5v9f4zpxanw3z",
        "type": "tarball",
        "url": "https://github.com/pastebinrun/pastebinrun/archive/bc6a669b107085d54c9dfd9f65ed402c3431460e.tar.gz",
        "url_template": "https://github.com/<owner>/<repo>/archive/<rev>.tar.gz"
    },
    "pulldown-cmark-babelmark": {
        "branch": "master",
        "description": null,
        "homepage": null,
        "owner": "xfix",
        "repo": "pulldown-cmark-babelmark",
        "rev": "fb114d855ababe7320c2e883a8d55fc637471d6a",
        "sha256": "1h5bpqxzarcrxk1b2baqakpzaapsdmihrkcv6275zldbx0qwg20k",
        "type": "tarball",
        "url": "https://github.com/xfix/pulldown-cmark-babelmark/archive/fb114d855ababe7320c2e883a8d55fc637471d6a.tar.gz",
        "url_template": "https://github.com/<owner>/<repo>/archive/<rev>.tar.gz"
    },
    "xbot": {
        "branch": "master",
        "description": null,
        "homepage": null,
        "owner": "xfix",
        "repo": "xbot",
        "rev": "393afafb05a6e0b1905c2397f815dc1cc008abb9",
        "sha256": "0fy3hqj414708z7cq31cma0lyifpl1d9m92n05v4psxhimirbiks",
        "type": "tarball",
        "url": "https://github.com/xfix/xbot/archive/393afafb05a6e0b1905c2397f815dc1cc008abb9.tar.gz",
        "url_template": "https://github.com/<owner>/<repo>/archive/<rev>.tar.gz"
    }
}
